pre_build_script/__init__.py
pre_build_script/pre_build_script.py
mkdocs_pre_build_script-0.1.0.dist-info/LICENSE
mkdocs_pre_build_script-0.1.0.dist-info/METADATA
mkdocs_pre_build_script-0.1.0.dist-info/WHEEL
mkdocs_pre_build_script-0.1.0.dist-info/entry_points.txt
mkdocs_pre_build_script-0.1.0.dist-info/top_level.txt
mkdocs_pre_build_script-0.1.0.dist-info/RECORD
