Metadata-Version: 2.2
Name: mkdocs-pre-build-script
Version: 0.1.0
Summary: A MkDocs plugin to run a Python script before build
Home-page: https://github.com/StudyPavilion/mkdocs_pre_build_script
Author: StudyPavilion
Author-email: studypavilion@163.com
License-File: LICENSE
Requires-Dist: mkdocs
Dynamic: author
Dynamic: author-email
Dynamic: description
Dynamic: description-content-type
Dynamic: home-page
Dynamic: requires-dist
Dynamic: summary
